autumn/__init__.py
autumn/_base_client.py
autumn/_client.py
autumn/_compat.py
autumn/_constants.py
autumn/_exceptions.py
autumn/_files.py
autumn/_models.py
autumn/_qs.py
autumn/_resource.py
autumn/_response.py
autumn/_streaming.py
autumn/_types.py
autumn/_version.py
autumn/py.typed
autumn/_utils/__init__.py
autumn/_utils/_compat.py
autumn/_utils/_datetime_parse.py
autumn/_utils/_logs.py
autumn/_utils/_proxy.py
autumn/_utils/_reflection.py
autumn/_utils/_resources_proxy.py
autumn/_utils/_streams.py
autumn/_utils/_sync.py
autumn/_utils/_transform.py
autumn/_utils/_typing.py
autumn/_utils/_utils.py
autumn/lib/.keep
autumn/resources/__init__.py
autumn/resources/balances.py
autumn/resources/customers.py
autumn/resources/entities.py
autumn/resources/events.py
autumn/resources/plans.py
autumn/resources/referrals.py
autumn/types/__init__.py
autumn/types/attach_response.py
autumn/types/balance_create_params.py
autumn/types/balance_create_response.py
autumn/types/balance_update_params.py
autumn/types/balance_update_response.py
autumn/types/billing_portal_response.py
autumn/types/cancel_response.py
autumn/types/check_response.py
autumn/types/checkout_response.py
autumn/types/client_attach_params.py
autumn/types/client_billing_portal_params.py
autumn/types/client_cancel_params.py
autumn/types/client_check_params.py
autumn/types/client_checkout_params.py
autumn/types/client_query_params.py
autumn/types/client_setup_payment_params.py
autumn/types/client_track_params.py
autumn/types/customer_create_params.py
autumn/types/customer_delete_response.py
autumn/types/customer_get_params.py
autumn/types/customer_list_params.py
autumn/types/customer_list_response.py
autumn/types/customer_update_params.py
autumn/types/entity_create_params.py
autumn/types/entity_delete_response.py
autumn/types/entity_get_params.py
autumn/types/event_aggregate_params.py
autumn/types/event_aggregate_response.py
autumn/types/event_list_params.py
autumn/types/event_list_response.py
autumn_sdk-0.5.0.dist-info/METADATA
autumn_sdk-0.5.0.dist-info/WHEEL
autumn_sdk-0.5.0.dist-info/licenses/LICENSE
autumn_sdk-0.5.0.dist-info/RECORD
